.gitignore
README.txt
bootstrap.py
buildout.cfg
setup.py
docs/Makefile
docs/changes.txt
docs/conf.py
docs/description.txt
docs/development.txt
docs/index.txt
docs/license.txt
docs/make.bat
docs/use.txt
src/buildout_versions/__init__.py
src/buildout_versions.egg-info/PKG-INFO
src/buildout_versions.egg-info/SOURCES.txt
src/buildout_versions.egg-info/dependency_links.txt
src/buildout_versions.egg-info/entry_points.txt
src/buildout_versions.egg-info/not-zip-safe
src/buildout_versions.egg-info/requires.txt
src/buildout_versions.egg-info/top_level.txt
src/buildout_versions/tests/__init__.py
src/buildout_versions/tests/test_constrain.py
src/buildout_versions/tests/test_docs.py
src/buildout_versions/tests/test_extension.py