Metadata-Version: 1.0
Name: buildout-versions
Version: 1.7
Summary: zc.buildout extension to display and record versions of packages used.
Home-page: http://packages.python.org/buildout-versions
Author: Chris Withers
Author-email: chris@simplistix.co.uk
License: MIT
Platform: UNKNOWN
Classifier: Development Status :: 5 - Production/Stable
Classifier: License :: OSI Approved :: MIT License
